tests/__init__.py
tests/test_ner_model.py
ArabSEA-0.1.0.dist-info/METADATA
ArabSEA-0.1.0.dist-info/WHEEL
ArabSEA-0.1.0.dist-info/entry_points.txt
ArabSEA-0.1.0.dist-info/top_level.txt
ArabSEA-0.1.0.dist-info/RECORD
